mcp_server_product/__init__.py
mcp_server_product/__main__.py
mcp_server_product/enums.py
mcp_server_product/models.py
mcp_server_product/server.py
mcp_server_product/service.py
mcp_server_product-0.2.0.dist-info/METADATA
mcp_server_product-0.2.0.dist-info/WHEEL
mcp_server_product-0.2.0.dist-info/entry_points.txt
mcp_server_product-0.2.0.dist-info/top_level.txt
mcp_server_product-0.2.0.dist-info/RECORD
