Metadata-Version: 2.4
Name: mcp-server-product
Version: 0.2.0
Summary: MCP server for product search and recommendation
Requires-Python: >=3.10
Requires-Dist: mcp>=1.0.0
Requires-Dist: pydantic>=2.0.0
